dict_aligned_print/__init__.py
dict_aligned_print_tests/__init__.py
dict_aligned_print_tests/test___init__.py
dict_aligned_print-0.1.2.dist-info/LICENSE
dict_aligned_print-0.1.2.dist-info/METADATA
dict_aligned_print-0.1.2.dist-info/WHEEL
dict_aligned_print-0.1.2.dist-info/top_level.txt
dict_aligned_print-0.1.2.dist-info/RECORD
