Metadata-Version: 2.1
Name: dict-aligned-print
Version: 0.1.2
Summary: print dict in aligned way
Home-page: https://github.com/lisrael1/dict_aligned_print
Author: Lior Israeli
Author-email: israelilior@gmail.com
License: UNKNOWN
Project-URL: Bug Tracker, https://github.com/lisrael1/dict_aligned_print/issues
Platform: UNKNOWN
Classifier: Programming Language :: Python :: 3
Classifier: License :: OSI Approved :: MIT License
Classifier: Operating System :: OS Independent
Requires-Python: >=3.6
License-File: LICENSE
